sharkey_crawler/__init__.py
sharkey_crawler/convert.py
sharkey_crawler/main.py
sharkey_crawler/types/__init__.py
sharkey_crawler/types/id.py
sharkey_crawler/types/post.py
sharkey_crawler/types/user.py
sharkey_crawler-0.1.0.dist-info/LICENSE
sharkey_crawler-0.1.0.dist-info/WHEEL
sharkey_crawler-0.1.0.dist-info/METADATA
sharkey_crawler-0.1.0.dist-info/RECORD
