Metadata-Version: 2.1
Name: sharkey-crawler
Version: 0.1.0
Summary: Python library to crawl user data from sharkey instances
Author-email: Leo <leo@hexafuchs.de>
Requires-Python: >=3.10.0
Classifier: Development Status :: 3 - Alpha
Classifier: Intended Audience :: Developers
Classifier: License :: OSI Approved :: MIT License
Classifier: Programming Language :: Python :: 3 :: Only
Classifier: Programming Language :: Python :: 3.10
Classifier: Programming Language :: Python :: 3.11
Classifier: Programming Language :: Python :: 3.12
Classifier: Programming Language :: Python :: 3.13
Requires-Dist: requests==2.32.3
Requires-Dist: pydantic==2.8.2
Requires-Dist: annotated-types==0.7.0
Requires-Dist: bpython ; extra == "dev"
Requires-Dist: pipdeptree ; extra == "dev"
Requires-Dist: sphinx ; extra == "doc"
Requires-Dist: sphinx-copybutton ; extra == "doc"
Requires-Dist: sphinx-rtd-theme ; extra == "doc"
Requires-Dist: sphinx-autodoc-typehints ; extra == "doc"
Requires-Dist: autodocsumm ; extra == "doc"
Requires-Dist: bandit[toml]==1.7.9 ; extra == "test"
Requires-Dist: black==24.4.2 ; extra == "test"
Requires-Dist: check-manifest==0.49 ; extra == "test"
Requires-Dist: flake8-bugbear==24.4.26 ; extra == "test"
Requires-Dist: flake8-docstrings ; extra == "test"
Requires-Dist: flake8-formatter_junit_xml ; extra == "test"
Requires-Dist: flake8 ; extra == "test"
Requires-Dist: flake8-pyproject ; extra == "test"
Requires-Dist: pre-commit==3.7.1 ; extra == "test"
Requires-Dist: pylint==3.2.5 ; extra == "test"
Requires-Dist: pylint_junit ; extra == "test"
Requires-Dist: pytest-cov==5.0.0 ; extra == "test"
Requires-Dist: pytest-mock<3.10.1 ; extra == "test"
Requires-Dist: pytest-runner ; extra == "test"
Requires-Dist: pytest==8.2.2 ; extra == "test"
Requires-Dist: pytest-github-actions-annotate-failures ; extra == "test"
Requires-Dist: shellcheck-py==0.10.0.1 ; extra == "test"
Requires-Dist: pyright ; extra == "test"
Requires-Dist: tox ; extra == "test"
Project-URL: Documentation, https://github.com/Hexafuchs/sharkey-crawler/tree/main#readme
Project-URL: Source, https://github.com/Hexafuchs/sharkey-crawler
Project-URL: Tracker, https://github.com/Hexafuchs/sharkey-crawler/issues
Provides-Extra: dev
Provides-Extra: doc
Provides-Extra: test
